varfxi/.ipynb_checkpoints/distGARCH-checkpoint.py
varfxi/.ipynb_checkpoints/joyplot2-checkpoint.py
varfxi/.ipynb_checkpoints/quantileproj-checkpoint.py
varfxi/__init__.py
varfxi/distGARCH.py
varfxi/joyplot2.py
varfxi/quantileproj.py
varfxi-0.0.4.dist-info/LICENSE
varfxi-0.0.4.dist-info/METADATA
varfxi-0.0.4.dist-info/WHEEL
varfxi-0.0.4.dist-info/RECORD
